py_entity_analytics/__init__.py
py_entity_analytics/entity_analytics.py
py_entity_analytics/http_clients/__init__.py
py_entity_analytics/http_clients/collections.py
py_entity_analytics/http_clients/configurations.py
py_entity_analytics/http_clients/documents.py
py_entity_analytics/http_clients/http_base.py
py_entity_analytics/http_clients/identities.py
py_entity_analytics/http_clients/references.py
py_entity_analytics/http_clients/sentences.py
py_entity_analytics/utils/linking_configuration.py
py_entity_analytics-0.0.1.dist-info/METADATA
py_entity_analytics-0.0.1.dist-info/WHEEL
py_entity_analytics-0.0.1.dist-info/RECORD
