Metadata-Version: 2.1
Name: py_entity_analytics
Version: 0.0.1
Summary: Toolkit for Agolo's Entity Analytics ... in Python!
Author: Muhammad Nashaat
Author-email: muhammad.nashaat@agolo.com
Requires-Python: >=3.10,<4.0
Classifier: Programming Language :: Python :: 3
Classifier: Programming Language :: Python :: 3.10
Classifier: Programming Language :: Python :: 3.11
Classifier: Programming Language :: Python :: 3.12
Requires-Dist: requests (==2.31.0)
Requires-Dist: tabulate (==0.9.0)
